LICENSE
MANIFEST.in
README.md
pyproject.toml
requirements.txt
setup.py
visonorm/VERSION
visonorm/__init__.py
visonorm/arguments.json
visonorm/global_variables.py
visonorm/utils.py
visonorm.egg-info/PKG-INFO
visonorm.egg-info/SOURCES.txt
visonorm.egg-info/dependency_links.txt
visonorm.egg-info/not-zip-safe
visonorm.egg-info/requires.txt
visonorm.egg-info/top_level.txt
visonorm/datasets/__init__.py
visonorm/datasets/downloader.py
visonorm/datasets/registry.py
visonorm/dictionary/__init__.py
visonorm/dictionary/dictionary.json
visonorm/lexnorm/__init__.py
visonorm/lexnorm/basic_normalizer.py
visonorm/lexnorm/detect.py
visonorm/lexnorm/emoji_handler.py
visonorm/lexnorm/normalize.py
visonorm/llm/__init__.py
visonorm/llm/gpt.py
visonorm/llm/prompts.py
visonorm/module/DataHandler.py
visonorm/module/Evaluator.py
visonorm/module/Logger.py
visonorm/module/config.py
visonorm/module/main.py
visonorm/module/optimization_utils.py
visonorm/module/requirements.txt
visonorm/module/script.txt
visonorm/module/upload_to_huggingface.py
visonorm/module/utils.py
visonorm/module/visonorm_bartpho_model.py
visonorm/module/visonorm_model.py
visonorm/module/visonorm_phobert_model.py
visonorm/module/visonorm_visobert_model.py
visonorm/module/visonorm_vit5_model.py
visonorm/module/base_model/Student.py
visonorm/module/base_model/ViSoNormalizer.py
visonorm/module/base_model/__init__.py
visonorm/module/base_model/model_construction/__init__.py
visonorm/module/base_model/model_construction/bartpho.py
visonorm/module/base_model/model_construction/binary_predictor.py
visonorm/module/base_model/model_construction/phobert.py
visonorm/module/base_model/model_construction/visobert.py
visonorm/module/base_model/model_construction/vit5.py
visonorm/module/core/__init__.py
visonorm/module/core/data.py
visonorm/module/core/evaluation.py
visonorm/module/core/models.py
visonorm/module/core/training_loop.py
visonorm/module/teacher/RuleAttentionNetwork.py
visonorm/module/teacher/Teacher.py
visonorm/module/teacher/__init__.py
visonorm/module/utils/__init__.py
visonorm/module/utils/regex_expression.py
visonorm/module/utils/text_preprocessing.py
visonorm/tasks/__init__.py
