Metadata-Version: 2.4
Name: visonorm
Version: 0.1.1
Summary: Vietnamese Social Media Lexical Normalization Toolkit
Home-page: https://github.com/AnhHoang0529/visonorm
Author: Ha Dung Nguyen
Author-email: Anh Thi-Hoang Nguyen <anhnth@uit.edu.vn>
Project-URL: Homepage, https://github.com/AnhHoang0529/visonorm
Project-URL: Documentation, https://github.com/AnhHoang0529/visonorm
Project-URL: Repository, https://github.com/AnhHoang0529/visonorm
Project-URL: Issues, https://github.com/AnhHoang0529/visonorm/issues
Classifier: Programming Language :: Python :: 3
Classifier: Programming Language :: Python :: 3.10
Classifier: Programming Language :: Python :: 3.11
Classifier: Programming Language :: Python :: 3.12
Classifier: License :: OSI Approved :: MIT License
Classifier: Operating System :: OS Independent
Classifier: Development Status :: 3 - Alpha
Classifier: Intended Audience :: Developers
Classifier: Intended Audience :: Science/Research
Classifier: Topic :: Software Development :: Libraries :: Python Modules
Classifier: Topic :: Text Processing :: Linguistic
Classifier: Topic :: Scientific/Engineering :: Artificial Intelligence
Requires-Python: >=3.10
License-File: LICENSE
Requires-Dist: transformers>=4.0.0
Requires-Dist: scikit-learn>=0.24.0
Requires-Dist: pandas>=1.3.0
Requires-Dist: requests>=2.25.0
Requires-Dist: tqdm>=4.60.0
Requires-Dist: numpy>=1.23.2
Requires-Dist: datasets
Requires-Dist: openai
Requires-Dist: sentencepiece
Requires-Dist: joblib
Requires-Dist: protobuf
Requires-Dist: emot
Requires-Dist: attridict
Requires-Dist: bs4
Requires-Dist: chardet
Requires-Dist: torch
Provides-Extra: dev
Requires-Dist: pytest>=6.0; extra == "dev"
Requires-Dist: black>=22.0; extra == "dev"
Requires-Dist: flake8>=4.0; extra == "dev"
Provides-Extra: cpu
Requires-Dist: torch>=1.10.0; extra == "cpu"
Requires-Dist: torchvision>=0.11.0; extra == "cpu"
Requires-Dist: torchaudio>=0.10.0; extra == "cpu"
Provides-Extra: gpu
Requires-Dist: torch>=1.10.0; extra == "gpu"
Requires-Dist: torchvision>=0.11.0; extra == "gpu"
Requires-Dist: torchaudio>=0.10.0; extra == "gpu"
Dynamic: author
Dynamic: home-page
Dynamic: license-file
Dynamic: requires-python
